sveltest/__init__.py
sveltest/__main__.py
sveltest/case.py
sveltest/caseview.py
sveltest/core.py
sveltest/loader.py
sveltest/models.py
sveltest/runner.py
sveltest/version.py
sveltest/version.py.bak
sveltest/bin/__init__.py
sveltest/bin/conf/__application_test.py
sveltest/bin/conf/__init__.py
sveltest/bin/conf/appconfig.py
sveltest/bin/conf/application.py
sveltest/bin/conf/cache_.py
sveltest/bin/conf/commandline.py
sveltest/bin/conf/env.py
sveltest/bin/conf/global_settings.py
sveltest/bin/conf/license.py
sveltest/bin/conf/_html/__init__.py
sveltest/bin/conf/_html/email_test_template01.html
sveltest/bin/conf/base/__init__.py
sveltest/bin/conf/base/sveltest_cli_gui.py
sveltest/bin/conf/base/sveltest_main.py
sveltest/bin/conf/base/_postmanExportjsonAnalysis/__init__.py
sveltest/bin/conf/base/_postmanExportjsonAnalysis/data.py
sveltest/bin/conf/base/_postmanExportjsonAnalysis/main.py
sveltest/bin/conf/base/_postmanExportjsonAnalysis/method_.py-tpl
sveltest/bin/conf/base/_postmanExportjsonAnalysis/method_get.py-tpl
sveltest/bin/conf/base/_postmanExportjsonAnalysis/method_post.py-tpl
sveltest/bin/conf/base/_postmanExportjsonAnalysis/method_put.py-tpl
sveltest/bin/conf/base/_postmanExportjsonAnalysis/template.py-tpl
sveltest/bin/conf/base/_postmanExportjsonAnalysis/test1.py
sveltest/bin/conf/base/_postmanExportjsonAnalysis/浏览器.postman_collection.json
sveltest/bin/conf/base/api_demo/__init__.py
sveltest/bin/conf/base/api_demo/api.py
sveltest/bin/conf/base/api_demo/cityids.json
sveltest/bin/conf/base/j/__init__.py
sveltest/bin/conf/base/j/manage.py-tpl
sveltest/bin/conf/base/j/case/__init__.py
sveltest/bin/conf/base/j/case/test_baidu.py-tpl
sveltest/bin/conf/base/j/common/__init__.py
sveltest/bin/conf/base/j/pages/BaiduElement.py-tpl
sveltest/bin/conf/base/j/pages/__init__.py
sveltest/bin/conf/base/j/project_name/PageBase.py-tpl
sveltest/bin/conf/base/j/project_name/__init__.py
sveltest/bin/conf/base/j/project_name/settings.py-tpl
sveltest/bin/conf/base/j/report/__init__.py
sveltest-1.0.2.dist-info/LICENSE
sveltest-1.0.2.dist-info/METADATA
sveltest-1.0.2.dist-info/WHEEL
sveltest-1.0.2.dist-info/entry_points.txt
sveltest-1.0.2.dist-info/top_level.txt
sveltest-1.0.2.dist-info/RECORD
