Metadata-Version: 2.1
Name: sveltest
Version: 1.0.2
Summary: 高效率测试开发集成框架
Home-page: https://github.com/sveltest-Team/sveltest
Author: guanfl
Author-email: gfl13453001@163.com
License: UNKNOWN
Keywords: sveltest linux python selenium unittest
Platform: UNKNOWN
Classifier: Development Status :: 4 - Beta
Classifier: Programming Language :: Python :: 3.7
Classifier: Programming Language :: Python :: 3.8
Classifier: Programming Language :: Python :: 3.9
Classifier: License :: OSI Approved :: MIT License
Classifier: Operating System :: OS Independent
Requires-Python: >=3.6
Requires-Dist: Pillow (==9.3.0)
Requires-Dist: selenium
Requires-Dist: testdata (==1.1.3)
Requires-Dist: PyMySQL (==0.9.3)
Requires-Dist: Faker (==3.0.0)
Requires-Dist: flanker
Requires-Dist: requests (==2.26.0)
Requires-Dist: rich (==10.12.0)
Requires-Dist: yagmail
Requires-Dist: jinja2
Requires-Dist: pyyaml
Requires-Dist: NextTestRunner
Requires-Dist: loguru (==0.6.0)
Requires-Dist: Click (==8.0.1)
Requires-Dist: xmltodict
Requires-Dist: win10toast ; sys_platform == "win32"
